{
  "openapi": "3.0.1",
  "info": {
    "title": "DesafioTechSub",
    "version": "1.0"
  },
  "paths": {
    "/api/Auth/login": {
      "post": {
        "tags": [
          "Auth"
        ],
        "requestBody": {
          "content": {
            "application/json": {
              "schema": {
                "$ref": "#/components/schemas/Login"
              }
            },
            "text/json": {
              "schema": {
                "$ref": "#/components/schemas/Login"
              }
            },
            "application/*+json": {
              "schema": {
                "$ref": "#/components/schemas/Login"
              }
            }
          }
        },
        "responses": {
          "200": {
            "description": "OK"
          }
        }
      }
    },
    "/api/PaymentMethod/create": {
      "post": {
        "tags": [
          "PaymentMethod"
        ],
        "requestBody": {
          "content": {
            "application/json": {
              "schema": {
                "$ref": "#/components/schemas/PaymentMethod"
              }
            },
            "text/json": {
              "schema": {
                "$ref": "#/components/schemas/PaymentMethod"
              }
            },
            "application/*+json": {
              "schema": {
                "$ref": "#/components/schemas/PaymentMethod"
              }
            }
          }
        },
        "responses": {
          "200": {
            "description": "OK",
            "content": {
              "text/plain": {
                "schema": {
                  "$ref": "#/components/schemas/PaymentMethod"
                }
              },
              "application/json": {
                "schema": {
                  "$ref": "#/components/schemas/PaymentMethod"
                }
              },
              "text/json": {
                "schema": {
                  "$ref": "#/components/schemas/PaymentMethod"
                }
              }
            }
          }
        }
      }
    },
    "/api/PaymentMethod/{id}": {
      "get": {
        "tags": [
          "PaymentMethod"
        ],
        "parameters": [
          {
            "name": "id",
            "in": "path",
            "required": true,
            "schema": {
              "type": "string",
              "format": "uuid"
            }
          }
        ],
        "responses": {
          "200": {
            "description": "OK",
            "content": {
              "text/plain": {
                "schema": {
                  "$ref": "#/components/schemas/PaymentMethod"
                }
              },
              "application/json": {
                "schema": {
                  "$ref": "#/components/schemas/PaymentMethod"
                }
              },
              "text/json": {
                "schema": {
                  "$ref": "#/components/schemas/PaymentMethod"
                }
              }
            }
          }
        }
      }
    },
    "/api/PaymentMethod": {
      "get": {
        "tags": [
          "PaymentMethod"
        ],
        "responses": {
          "200": {
            "description": "OK",
            "content": {
              "text/plain": {
                "schema": {
                  "type": "array",
                  "items": {
                    "$ref": "#/components/schemas/PaymentMethod"
                  }
                }
              },
              "application/json": {
                "schema": {
                  "type": "array",
                  "items": {
                    "$ref": "#/components/schemas/PaymentMethod"
                  }
                }
              },
              "text/json": {
                "schema": {
                  "type": "array",
                  "items": {
                    "$ref": "#/components/schemas/PaymentMethod"
                  }
                }
              }
            }
          }
        }
      }
    },
    "/api/PaymentMethod/delete/{id}": {
      "delete": {
        "tags": [
          "PaymentMethod"
        ],
        "parameters": [
          {
            "name": "id",
            "in": "path",
            "required": true,
            "schema": {
              "type": "string",
              "format": "uuid"
            }
          }
        ],
        "responses": {
          "200": {
            "description": "OK"
          }
        }
      }
    },
    "/api/Subscription/create": {
      "post": {
        "tags": [
          "Subscription"
        ],
        "requestBody": {
          "content": {
            "application/json": {
              "schema": {
                "$ref": "#/components/schemas/Subscription"
              }
            },
            "text/json": {
              "schema": {
                "$ref": "#/components/schemas/Subscription"
              }
            },
            "application/*+json": {
              "schema": {
                "$ref": "#/components/schemas/Subscription"
              }
            }
          }
        },
        "responses": {
          "200": {
            "description": "OK",
            "content": {
              "text/plain": {
                "schema": {
                  "$ref": "#/components/schemas/Subscription"
                }
              },
              "application/json": {
                "schema": {
                  "$ref": "#/components/schemas/Subscription"
                }
              },
              "text/json": {
                "schema": {
                  "$ref": "#/components/schemas/Subscription"
                }
              }
            }
          }
        }
      }
    },
    "/api/Subscription/{id}": {
      "get": {
        "tags": [
          "Subscription"
        ],
        "parameters": [
          {
            "name": "id",
            "in": "path",
            "required": true,
            "schema": {
              "type": "string",
              "format": "uuid"
            }
          }
        ],
        "responses": {
          "200": {
            "description": "OK",
            "content": {
              "text/plain": {
                "schema": {
                  "$ref": "#/components/schemas/Subscription"
                }
              },
              "application/json": {
                "schema": {
                  "$ref": "#/components/schemas/Subscription"
                }
              },
              "text/json": {
                "schema": {
                  "$ref": "#/components/schemas/Subscription"
                }
              }
            }
          }
        }
      }
    },
    "/api/Subscription": {
      "get": {
        "tags": [
          "Subscription"
        ],
        "responses": {
          "200": {
            "description": "OK",
            "content": {
              "text/plain": {
                "schema": {
                  "type": "array",
                  "items": {
                    "$ref": "#/components/schemas/Subscription"
                  }
                }
              },
              "application/json": {
                "schema": {
                  "type": "array",
                  "items": {
                    "$ref": "#/components/schemas/Subscription"
                  }
                }
              },
              "text/json": {
                "schema": {
                  "type": "array",
                  "items": {
                    "$ref": "#/components/schemas/Subscription"
                  }
                }
              }
            }
          }
        }
      }
    },
    "/api/Subscription/delete/{id}": {
      "delete": {
        "tags": [
          "Subscription"
        ],
        "parameters": [
          {
            "name": "id",
            "in": "path",
            "required": true,
            "schema": {
              "type": "string",
              "format": "uuid"
            }
          }
        ],
        "responses": {
          "200": {
            "description": "OK"
          }
        }
      }
    },
    "/api/Subscription/cancel": {
      "post": {
        "tags": [
          "Subscription"
        ],
        "parameters": [
          {
            "name": "id",
            "in": "query",
            "schema": {
              "type": "string",
              "format": "uuid"
            }
          }
        ],
        "responses": {
          "200": {
            "description": "OK",
            "content": {
              "text/plain": {
                "schema": {
                  "$ref": "#/components/schemas/Subscription"
                }
              },
              "application/json": {
                "schema": {
                  "$ref": "#/components/schemas/Subscription"
                }
              },
              "text/json": {
                "schema": {
                  "$ref": "#/components/schemas/Subscription"
                }
              }
            }
          }
        }
      }
    },
    "/api/Subscription/report/getMonthlyRevenue": {
      "get": {
        "tags": [
          "Subscription"
        ],
        "responses": {
          "200": {
            "description": "OK",
            "content": {
              "text/plain": {
                "schema": {
                  "type": "array",
                  "items": {
                    "$ref": "#/components/schemas/RevenueReport"
                  }
                }
              },
              "application/json": {
                "schema": {
                  "type": "array",
                  "items": {
                    "$ref": "#/components/schemas/RevenueReport"
                  }
                }
              },
              "text/json": {
                "schema": {
                  "type": "array",
                  "items": {
                    "$ref": "#/components/schemas/RevenueReport"
                  }
                }
              }
            }
          }
        }
      }
    },
    "/api/SubscriptionPlan/create": {
      "post": {
        "tags": [
          "SubscriptionPlan"
        ],
        "requestBody": {
          "content": {
            "application/json": {
              "schema": {
                "$ref": "#/components/schemas/SubscriptionPlan"
              }
            },
            "text/json": {
              "schema": {
                "$ref": "#/components/schemas/SubscriptionPlan"
              }
            },
            "application/*+json": {
              "schema": {
                "$ref": "#/components/schemas/SubscriptionPlan"
              }
            }
          }
        },
        "responses": {
          "200": {
            "description": "OK",
            "content": {
              "text/plain": {
                "schema": {
                  "$ref": "#/components/schemas/SubscriptionPlan"
                }
              },
              "application/json": {
                "schema": {
                  "$ref": "#/components/schemas/SubscriptionPlan"
                }
              },
              "text/json": {
                "schema": {
                  "$ref": "#/components/schemas/SubscriptionPlan"
                }
              }
            }
          }
        }
      }
    },
    "/api/SubscriptionPlan/{id}": {
      "get": {
        "tags": [
          "SubscriptionPlan"
        ],
        "parameters": [
          {
            "name": "id",
            "in": "path",
            "required": true,
            "schema": {
              "type": "string",
              "format": "uuid"
            }
          }
        ],
        "responses": {
          "200": {
            "description": "OK",
            "content": {
              "text/plain": {
                "schema": {
                  "$ref": "#/components/schemas/SubscriptionPlan"
                }
              },
              "application/json": {
                "schema": {
                  "$ref": "#/components/schemas/SubscriptionPlan"
                }
              },
              "text/json": {
                "schema": {
                  "$ref": "#/components/schemas/SubscriptionPlan"
                }
              }
            }
          }
        }
      }
    },
    "/api/SubscriptionPlan": {
      "get": {
        "tags": [
          "SubscriptionPlan"
        ],
        "responses": {
          "200": {
            "description": "OK",
            "content": {
              "text/plain": {
                "schema": {
                  "type": "array",
                  "items": {
                    "$ref": "#/components/schemas/SubscriptionPlan"
                  }
                }
              },
              "application/json": {
                "schema": {
                  "type": "array",
                  "items": {
                    "$ref": "#/components/schemas/SubscriptionPlan"
                  }
                }
              },
              "text/json": {
                "schema": {
                  "type": "array",
                  "items": {
                    "$ref": "#/components/schemas/SubscriptionPlan"
                  }
                }
              }
            }
          }
        }
      }
    },
    "/api/SubscriptionPlan/delete/{id}": {
      "delete": {
        "tags": [
          "SubscriptionPlan"
        ],
        "parameters": [
          {
            "name": "id",
            "in": "path",
            "required": true,
            "schema": {
              "type": "string",
              "format": "uuid"
            }
          }
        ],
        "responses": {
          "200": {
            "description": "OK"
          }
        }
      }
    },
    "/api/User/create": {
      "post": {
        "tags": [
          "User"
        ],
        "requestBody": {
          "content": {
            "application/json": {
              "schema": {
                "$ref": "#/components/schemas/User"
              }
            },
            "text/json": {
              "schema": {
                "$ref": "#/components/schemas/User"
              }
            },
            "application/*+json": {
              "schema": {
                "$ref": "#/components/schemas/User"
              }
            }
          }
        },
        "responses": {
          "200": {
            "description": "OK",
            "content": {
              "text/plain": {
                "schema": {
                  "$ref": "#/components/schemas/User"
                }
              },
              "application/json": {
                "schema": {
                  "$ref": "#/components/schemas/User"
                }
              },
              "text/json": {
                "schema": {
                  "$ref": "#/components/schemas/User"
                }
              }
            }
          }
        }
      }
    },
    "/api/User/update": {
      "post": {
        "tags": [
          "User"
        ],
        "requestBody": {
          "content": {
            "application/json": {
              "schema": {
                "$ref": "#/components/schemas/User"
              }
            },
            "text/json": {
              "schema": {
                "$ref": "#/components/schemas/User"
              }
            },
            "application/*+json": {
              "schema": {
                "$ref": "#/components/schemas/User"
              }
            }
          }
        },
        "responses": {
          "200": {
            "description": "OK",
            "content": {
              "text/plain": {
                "schema": {
                  "$ref": "#/components/schemas/User"
                }
              },
              "application/json": {
                "schema": {
                  "$ref": "#/components/schemas/User"
                }
              },
              "text/json": {
                "schema": {
                  "$ref": "#/components/schemas/User"
                }
              }
            }
          }
        }
      }
    },
    "/api/User/{id}": {
      "get": {
        "tags": [
          "User"
        ],
        "parameters": [
          {
            "name": "id",
            "in": "path",
            "required": true,
            "schema": {
              "type": "string",
              "format": "uuid"
            }
          }
        ],
        "responses": {
          "200": {
            "description": "OK",
            "content": {
              "text/plain": {
                "schema": {
                  "$ref": "#/components/schemas/User"
                }
              },
              "application/json": {
                "schema": {
                  "$ref": "#/components/schemas/User"
                }
              },
              "text/json": {
                "schema": {
                  "$ref": "#/components/schemas/User"
                }
              }
            }
          }
        }
      }
    },
    "/api/User": {
      "get": {
        "tags": [
          "User"
        ],
        "responses": {
          "200": {
            "description": "OK",
            "content": {
              "text/plain": {
                "schema": {
                  "type": "array",
                  "items": {
                    "$ref": "#/components/schemas/User"
                  }
                }
              },
              "application/json": {
                "schema": {
                  "type": "array",
                  "items": {
                    "$ref": "#/components/schemas/User"
                  }
                }
              },
              "text/json": {
                "schema": {
                  "type": "array",
                  "items": {
                    "$ref": "#/components/schemas/User"
                  }
                }
              }
            }
          }
        }
      }
    },
    "/api/User/delete/{id}": {
      "delete": {
        "tags": [
          "User"
        ],
        "parameters": [
          {
            "name": "id",
            "in": "path",
            "required": true,
            "schema": {
              "type": "string",
              "format": "uuid"
            }
          }
        ],
        "responses": {
          "200": {
            "description": "OK"
          }
        }
      }
    },
    "/api/User/report/getCurrentUsersBySubscription": {
      "get": {
        "tags": [
          "User"
        ],
        "responses": {
          "200": {
            "description": "OK",
            "content": {
              "text/plain": {
                "schema": {
                  "type": "array",
                  "items": {
                    "$ref": "#/components/schemas/UserReport"
                  }
                }
              },
              "application/json": {
                "schema": {
                  "type": "array",
                  "items": {
                    "$ref": "#/components/schemas/UserReport"
                  }
                }
              },
              "text/json": {
                "schema": {
                  "type": "array",
                  "items": {
                    "$ref": "#/components/schemas/UserReport"
                  }
                }
              }
            }
          }
        }
      }
    }
  },
  "components": {
    "schemas": {
      "Login": {
        "type": "object",
        "properties": {
          "username": {
            "type": "string",
            "nullable": true
          },
          "password": {
            "type": "string",
            "nullable": true
          }
        },
        "additionalProperties": false
      },
      "PaymentMethod": {
        "required": [
          "name"
        ],
        "type": "object",
        "properties": {
          "id": {
            "type": "string",
            "format": "uuid",
            "nullable": true
          },
          "name": {
            "maxLength": 50,
            "minLength": 0,
            "type": "string"
          }
        },
        "additionalProperties": false
      },
      "RevenueReport": {
        "type": "object",
        "properties": {
          "month": {
            "type": "integer",
            "format": "int32"
          },
          "revenue": {
            "type": "number",
            "format": "double"
          }
        },
        "additionalProperties": false
      },
      "Subscription": {
        "required": [
          "chargeDate",
          "isCanceled",
          "subscriptionPlanId",
          "subscriptionValue",
          "userId"
        ],
        "type": "object",
        "properties": {
          "id": {
            "type": "string",
            "format": "uuid",
            "nullable": true
          },
          "userId": {
            "type": "string",
            "format": "uuid"
          },
          "subscriptionPlanId": {
            "type": "string",
            "format": "uuid"
          },
          "subscriptionValue": {
            "type": "number",
            "format": "double"
          },
          "chargeDate": {
            "type": "string",
            "format": "date-time"
          },
          "isCanceled": {
            "type": "boolean"
          }
        },
        "additionalProperties": false
      },
      "SubscriptionPlan": {
        "required": [
          "allowTrial",
          "anualPrice",
          "monthlyPrice",
          "name"
        ],
        "type": "object",
        "properties": {
          "id": {
            "type": "string",
            "format": "uuid",
            "nullable": true
          },
          "name": {
            "minLength": 1,
            "type": "string"
          },
          "monthlyPrice": {
            "type": "number",
            "format": "double"
          },
          "anualPrice": {
            "type": "number",
            "format": "double"
          },
          "allowTrial": {
            "type": "boolean"
          }
        },
        "additionalProperties": false
      },
      "User": {
        "required": [
          "email",
          "isSubscriptionActive",
          "isTrialExpired",
          "password",
          "username"
        ],
        "type": "object",
        "properties": {
          "id": {
            "type": "string",
            "format": "uuid"
          },
          "username": {
            "maxLength": 50,
            "minLength": 0,
            "type": "string"
          },
          "email": {
            "maxLength": 50,
            "minLength": 0,
            "type": "string"
          },
          "password": {
            "maxLength": 50,
            "minLength": 0,
            "type": "string"
          },
          "paymentMethodId": {
            "type": "string",
            "format": "uuid",
            "nullable": true
          },
          "isSubscriptionActive": {
            "type": "boolean"
          },
          "isTrialExpired": {
            "type": "boolean"
          }
        },
        "additionalProperties": false
      },
      "UserReport": {
        "type": "object",
        "properties": {
          "user": {
            "type": "string",
            "nullable": true
          },
          "subscriptionPlan": {
            "type": "string",
            "nullable": true
          }
        },
        "additionalProperties": false
      }
    }
  }
}